{"sex": "F", "races": {"Hallwilerseelauf, Beinwil am See": {"race": "Hallwilerseelauf, Beinwil am See", "date": {"sam. 11.10.2014": {"weekday": "saturday", "year": 2014, "categories": {"21-F40": {"pace": 376000000000, "rank": 260, "distance": 21, "time": 7949.0}}, "day": 11, "month": 10, "livingplace": "Mumliswil"}, "sam. 10.10.2015": {"weekday": "saturday", "year": 2015, "categories": {"21-F50": {"pace": 396000000000, "rank": 120, "distance": 21, "time": 8374.3}}, "day": 10, "month": 10, "livingplace": "Mumliswil"}}, "location": "Beinwil am See"}}, "name": "Ackermann Anita", "birth": 1965}