{"sex": "M", "races": {"Zermatt Marathon, Zermatt": {"race": "Zermatt Marathon, Zermatt", "date": {"sam. 06.07.2002": {"weekday": "saturday", "year": 2002, "categories": {"M40": {"pace": 596000000000, "rank": 158, "distance": 42, "time": 25183.0}}, "day": 6, "month": 7, "livingplace": "Stuttgart"}}, "location": "Zermatt"}, "Jungfrau-Marathon, Interlaken": {"race": "Jungfrau-Marathon, Interlaken", "date": {"sam. 01.09.2001": {"weekday": "saturday", "year": 2001, "categories": {"M40": {"pace": 471000000000, "rank": 470, "distance": 42, "time": 19894.0}}, "day": 1, "month": 9, "livingplace": "Stuttgart"}}, "location": "Interlaken"}}, "name": "Apfelthaler Gerhard", "birth": 1961}