{"sex": "M", "races": {"Hallwilerseelauf, Beinwil am See": {"race": "Hallwilerseelauf, Beinwil am See", "date": {"sam. 14.10.2006": {"weekday": "saturday", "year": 2006, "categories": {"M30": {"pace": 268000000000, "rank": 214, "distance": 21, "time": 5672.1}}, "day": 14, "month": 10, "livingplace": "raft zug"}}, "location": "Beinwil am See"}, "ASICS Bremgarter Reusslauf": {"race": "ASICS Bremgarter Reusslauf", "longitude": 8.3397905, "latitude": 47.34917739999999, "date": {"sam. 25.02.2006": {"weekday": "saturday", "year": 2006, "categories": {"M30": {"pace": 246000000000, "rank": 143, "distance": 11, "time": 2586.4}}, "day": 25, "month": 2, "livingplace": "raft zug"}}, "location": "Bremgarten AG"}}, "name": "Augsburger Thierry", "birth": 0}