{"sex": "M", "races": {"Course de l'Escalade, Gen\u00e8ve": {"race": "Course de l'Escalade, Gen\u00e8ve", "longitude": 6.1431577, "latitude": 46.2043907, "date": {"sam. 03.12.2011": {"weekday": "saturday", "year": 2011, "categories": {"H-Elite": {"pace": 183000000000, "rank": 19, "distance": 7, "time": 1330.8}}, "day": 3, "month": 12, "livingplace": "Munchenstein"}}, "location": "Gen\u00e8ve"}, "Augusta Raurica Lauf, Augst BL": {"race": "Augusta Raurica Lauf, Augst BL", "date": {"dim. 13.11.2011": {"weekday": "sunday", "year": 2011, "categories": {"12-M30": {"pace": 189000000000, "rank": 1, "distance": 12, "time": 2268.5}}, "day": 13, "month": 11, "livingplace": "Munchenstein"}}, "location": "Augst BL"}, "crossrun, Therwil": {"race": "crossrun, Therwil", "longitude": 7.5532808, "latitude": 47.4990611, "date": {"dim. 28.08.2011": {"weekday": "sunday", "year": 2011, "categories": {"M30": {"pace": 199000000000, "rank": 2, "distance": 10, "time": 1995.5}}, "day": 28, "month": 8, "livingplace": "Munchenstein"}}, "location": "Therwil"}, "IWB Basel Marathon": {"race": "IWB Basel Marathon", "longitude": 7.5885761, "latitude": 47.5595986, "date": {"dim. 11.09.2011": {"weekday": "sunday", "year": 2011, "categories": {"H-21-M30": {"pace": 193000000000, "rank": 1, "distance": 21, "time": 4090.7}}, "day": 11, "month": 9, "livingplace": "Munchenstein"}}, "location": "Basel"}}, "name": "Berhane Ogubit", "birth": 1978}