{"sex": "M", "races": {"Engadiner Sommerlauf, Samedan": {"race": "Engadiner Sommerlauf, Samedan", "date": {"dim. 25.08.2002": {"weekday": "sunday", "year": 2002, "categories": {"SM1": {"pace": 256000000000, "rank": 8, "distance": 11, "time": 2689.7}}, "day": 25, "month": 8, "livingplace": "Santa Maria Rezzonico"}, "dim. 26.08.2001": {"weekday": "sunday", "year": 2001, "categories": {"SM1": {"pace": 277000000000, "rank": 18, "distance": 11, "time": 2914.1}}, "day": 26, "month": 8, "livingplace": "Coccaglio"}}, "location": "Bever"}}, "name": "Bongiasca Mario", "birth": 1960}