{"sex": "M", "races": {"Pfingstlauf Wohlen AG": {"race": "Pfingstlauf Wohlen AG", "longitude": 8.2768762, "latitude": 47.3493653, "date": {"sam. 03.06.2006": {"weekday": "saturday", "year": 2006, "categories": {"M50": {"pace": 271000000000, "rank": 56, "distance": 8, "time": 2225.0}}, "day": 3, "month": 6, "livingplace": "Anglikon"}}, "location": "Wohlen AG"}, "Hallwilerseelauf, Beinwil am See": {"race": "Hallwilerseelauf, Beinwil am See", "date": {"sam. 14.10.2000": {"weekday": "saturday", "year": 2000, "categories": {"31": {"pace": 266000000000, "rank": 54, "distance": 8, "time": 2133.0}}, "day": 14, "month": 10, "livingplace": "Wohlen"}, "sam. 14.10.2006": {"weekday": "saturday", "year": 2006, "categories": {"M50": {"pace": 322000000000, "rank": 257, "distance": 21, "time": 6802.4}}, "day": 14, "month": 10, "livingplace": "Anglikon"}}, "location": "Beinwil am See"}, "ASICS Bremgarter Reusslauf": {"race": "ASICS Bremgarter Reusslauf", "longitude": 8.3397905, "latitude": 47.34917739999999, "date": {"sam. 25.02.2006": {"weekday": "saturday", "year": 2006, "categories": {"M50": {"pace": 282000000000, "rank": 166, "distance": 11, "time": 2964.0}}, "day": 25, "month": 2, "livingplace": "Anglikon"}}, "location": "Bremgarten AG"}}, "name": "Brunner Bruno", "birth": 1951}