{"sex": "M", "races": {"Bieler Lauftage, Biel Bienne": {"race": "Bieler Lauftage, Biel Bienne", "longitude": 7.2467909, "latitude": 47.1367785, "date": {"ven. 17.06.2005": {"weekday": "friday", "year": 2005, "categories": {"H/M45": {"pace": 262000000000, "rank": 1, "distance": 21, "time": 5544.5}}, "day": 17, "month": 6, "livingplace": "Martigny"}}, "location": "Biel/Bienne"}, "Sierre-Zinal, Sierre": {"race": "Sierre-Zinal, Sierre", "longitude": 7.533536199999999, "latitude": 46.29413110000001, "date": {"dim. 11.08.2013": {"weekday": "sunday", "year": 2013, "categories": {"V\u00e9t_II": {"pace": 457000000000, "rank": 23, "distance": 31, "time": 14192.5}}, "day": 11, "month": 8, "livingplace": "Martigny"}}, "location": "Sierre"}, "Tour du Chablais #3 Bex": {"race": "Tour du Chablais #3 Bex", "longitude": 7.0223787, "latitude": 46.1782231, "date": {"mer. 21.04.2010": {"weekday": "wednesday", "year": 2010, "categories": {"M-M50": {"pace": 249000000000, "rank": 8, "distance": 10, "time": 2499.0}}, "day": 21, "month": 4, "livingplace": "Sion"}}, "location": "Evionnaz"}, "Tour du Chablais #1 Martigny": {"race": "Tour du Chablais #1 Martigny", "longitude": 6.9916269, "latitude": 46.2957462, "date": {"mer. 23.04.2014": {"weekday": "wednesday", "year": 2014, "categories": {"M-M50": {"pace": 321000000000, "rank": 90, "distance": 9, "time": 2735.7}}, "day": 23, "month": 4, "livingplace": "Martigny"}}, "location": "Ollon VD"}, "Z\u00fcrich Marathon, Teamrun und Cityrun": {"race": "Z\u00fcrich Marathon, Teamrun und Cityrun", "longitude": 8.541694, "latitude": 47.3768866, "date": {"dim. 09.04.2006": {"weekday": "sunday", "year": 2006, "categories": {"M50": {"pace": 276000000000, "rank": 32, "distance": 42, "time": 11672.3}}, "day": 9, "month": 4, "livingplace": "Martigny"}, "dim. 03.04.2005": {"weekday": "sunday", "year": 2005, "categories": {"M45": {"pace": 277000000000, "rank": 104, "distance": 42, "time": 11694.8}}, "day": 3, "month": 4, "livingplace": "Martigny"}, "dim. 20.04.2008": {"weekday": "sunday", "year": 2008, "categories": {"M50": {"pace": 276000000000, "rank": 59, "distance": 42, "time": 11677.9}}, "day": 20, "month": 4, "livingplace": "Martigny"}}, "location": "Z\u00fcrich"}, "Morat-Fribourg": {"race": "Morat-Fribourg", "longitude": 7.120184, "latitude": 46.92922110000001, "date": {"sam. 04.10.2014": {"weekday": "saturday", "year": 2014, "categories": {"17-M55": {"pace": 276000000000, "rank": 25, "distance": 17, "time": 4739.2}}, "day": 4, "month": 10, "livingplace": "Martigny"}, "dim. 05.10.2003": {"weekday": "sunday", "year": 2003, "categories": {"M45": {"pace": 250000000000, "rank": 34, "distance": 17, "time": 4293.8}}, "day": 5, "month": 10, "livingplace": "Martigny"}, "sam. 04.10.2008": {"weekday": "saturday", "year": 2008, "categories": {"C-M50": {"pace": 257000000000, "rank": 26, "distance": 17, "time": 4424.8}}, "day": 4, "month": 10, "livingplace": "Martigny"}, "sam. 05.10.2013": {"weekday": "saturday", "year": 2013, "categories": {"17-M55": {"pace": 265000000000, "rank": 14, "distance": 17, "time": 4637.1}}, "day": 5, "month": 10, "livingplace": "Martigny"}, "sam. 06.10.2012": {"weekday": "saturday", "year": 2012, "categories": {"17-M55": {"pace": 271000000000, "rank": 18, "distance": 17, "time": 4736.7}}, "day": 6, "month": 10, "livingplace": "Martigny"}, "dim. 07.10.2001": {"weekday": "sunday", "year": 2001, "categories": {"M45": {"pace": 259000000000, "rank": 59, "distance": 17, "time": 4449.6}}, "day": 7, "month": 10, "livingplace": "Martigny"}, "dim. 06.10.2002": {"weekday": "sunday", "year": 2002, "categories": {"M45": {"pace": 256000000000, "rank": 51, "distance": 17, "time": 4412.2}}, "day": 6, "month": 10, "livingplace": "Martigny"}, "sam. 06.10.2007": {"weekday": "saturday", "year": 2007, "categories": {"C/M50": {"pace": 257000000000, "rank": 32, "distance": 17, "time": 4423.5}}, "day": 6, "month": 10, "livingplace": "Martigny"}, "sam. 01.10.2011": {"weekday": "saturday", "year": 2011, "categories": {"17-M55": {"pace": 269000000000, "rank": 19, "distance": 17, "time": 4619.5}}, "day": 1, "month": 10, "livingplace": "Martigny"}}, "location": "Murten"}, "Jungfrau-Marathon, Interlaken": {"race": "Jungfrau-Marathon, Interlaken", "date": {"sam. 06.09.2003": {"weekday": "saturday", "year": 2003, "categories": {"M45": {"pace": 359000000000, "rank": 43, "distance": 42, "time": 15165.3}}, "day": 6, "month": 9, "livingplace": "Martigny"}}, "location": "Interlaken"}, "Kerzerslauf": {"race": "Kerzerslauf", "longitude": 7.1954365, "latitude": 46.97488999999999, "date": {"sam. 17.03.2012": {"weekday": "saturday", "year": 2012, "categories": {"15-M55": {"pace": 261000000000, "rank": 28, "distance": 15, "time": 3917.4}}, "day": 17, "month": 3, "livingplace": "Martigny"}, "sam. 20.03.2004": {"weekday": "saturday", "year": 2004, "categories": {"M45": {"pace": 237000000000, "rank": 24, "distance": 15, "time": 3558.3}}, "day": 20, "month": 3, "livingplace": "Martigny"}, "sam. 19.03.2011": {"weekday": "saturday", "year": 2011, "categories": {"15-M55": {"pace": 246000000000, "rank": 9, "distance": 15, "time": 3699.8}}, "day": 19, "month": 3, "livingplace": "Martigny"}, "sam. 15.03.2008": {"weekday": "saturday", "year": 2008, "categories": {"15/M50": {"pace": 257000000000, "rank": 57, "distance": 15, "time": 3858.6}}, "day": 15, "month": 3, "livingplace": "Martigny"}, "sam. 17.03.2007": {"weekday": "saturday", "year": 2007, "categories": {"M50": {"pace": 238000000000, "rank": 26, "distance": 15, "time": 3584.6}}, "day": 17, "month": 3, "livingplace": "Martigny"}, "sam. 18.03.2006": {"weekday": "saturday", "year": 2006, "categories": {"M50": {"pace": 242000000000, "rank": 13, "distance": 15, "time": 3639.3}}, "day": 18, "month": 3, "livingplace": "Martigny"}, "sam. 21.03.2009": {"weekday": "saturday", "year": 2009, "categories": {"15-M50": {"pace": 253000000000, "rank": 44, "distance": 15, "time": 3799.7}}, "day": 21, "month": 3, "livingplace": "Martigny"}, "sam. 15.03.2003": {"weekday": "saturday", "year": 2003, "categories": {"M45": {"pace": 234000000000, "rank": 26, "distance": 15, "time": 3522.4}}, "day": 15, "month": 3, "livingplace": "Martigny"}}, "location": "Kerzers"}, "Lausanne Marathon": {"race": "Lausanne Marathon", "longitude": 6.6322734, "latitude": 46.5196535, "date": {"dim. 26.10.2014": {"weekday": "sunday", "year": 2014, "categories": {"10-H50": {"pace": 332000000000, "rank": 229, "distance": 10, "time": 3329.2}}, "day": 26, "month": 10, "livingplace": "Martigny"}, "sam. 24.10.2015": {"weekday": "saturday", "year": 2015, "categories": {"10-H50": {"pace": 256000000000, "rank": 52, "distance": 10, "time": 2568.6}}, "day": 24, "month": 10, "livingplace": "Martigny"}}, "location": "Lausanne"}}, "name": "Closuit Bertrand", "birth": 1956}