{"sex": "F", "races": {"Hallwilerseelauf, Beinwil am See": {"race": "Hallwilerseelauf, Beinwil am See", "date": {"sam. 12.10.2013": {"weekday": "saturday", "year": 2013, "categories": {"10-Frau": {"pace": 358000000000, "rank": 453, "distance": 10, "time": 3580.0}}, "day": 12, "month": 10, "livingplace": "Zurich"}, "sam. 11.10.2014": {"weekday": "saturday", "year": 2014, "categories": {"21-F20": {"pace": 405000000000, "rank": 234, "distance": 21, "time": 8547.4}}, "day": 11, "month": 10, "livingplace": "Zurich"}}, "location": "Beinwil am See"}}, "name": "De Capitani Laura", "birth": 1989}