{"sex": "M", "races": {"Wylandlauf, Andelfingen": {"race": "Wylandlauf, Andelfingen", "date": {"sam. 18.06.2005": {"weekday": "saturday", "year": 2005, "categories": {"C": {"pace": 295000000000, "rank": 106, "distance": 15, "time": 4425.9}}, "day": 18, "month": 6, "livingplace": "Trullikon"}, "sam. 19.06.2004": {"weekday": "saturday", "year": 2004, "categories": {"C": {"pace": 273000000000, "rank": 94, "distance": 15, "time": 4102.6}}, "day": 19, "month": 6, "livingplace": "Trullikon"}}, "location": "Andelfingen"}, "Dietiker Neujahrslauf, Dietikon": {"race": "Dietiker Neujahrslauf, Dietikon", "longitude": 8.39977, "latitude": 47.4053885, "date": {"sam. 11.01.2003": {"weekday": "saturday", "year": 2003, "categories": {"C": {"pace": 271000000000, "rank": 160, "distance": 12, "time": 3289.7}}, "day": 11, "month": 1, "livingplace": "Trullikon"}}, "location": "Dietikon"}, "Laufsporttag Winterthur": {"race": "Laufsporttag Winterthur", "longitude": -75.6037351, "latitude": 39.8088766, "date": {"sam. 01.03.2003": {"weekday": "saturday", "year": 2003, "categories": {"C": {"pace": 285000000000, "rank": 118, "distance": 11, "time": 3001.2}}, "day": 1, "month": 3, "livingplace": "Trullikon"}, "sam. 06.03.2004": {"weekday": "saturday", "year": 2004, "categories": {"C": {"pace": 290000000000, "rank": 150, "distance": 11, "time": 3197.4}}, "day": 6, "month": 3, "livingplace": "Trullikon"}, "sam. 05.03.2005": {"weekday": "saturday", "year": 2005, "categories": {"C": {"pace": 299000000000, "rank": 115, "distance": 11, "time": 3296.3}}, "day": 5, "month": 3, "livingplace": "Trullikon"}}, "location": "Winterthur"}, "GP der Stadt D\u00fcbendorf": {"race": "GP der Stadt D\u00fcbendorf", "longitude": 8.618012799999999, "latitude": 47.3971476, "date": {"sam. 05.04.2003": {"weekday": "saturday", "year": 2003, "categories": {"C": {"pace": 267000000000, "rank": 143, "distance": 13, "time": 3369.0}}, "day": 5, "month": 4, "livingplace": "Trullikon"}, "sam. 03.04.2004": {"weekday": "saturday", "year": 2004, "categories": {"C": {"pace": 263000000000, "rank": 72, "distance": 13, "time": 3319.4}}, "day": 3, "month": 4, "livingplace": "Trullikon"}}, "location": "D\u00fcbendorf"}}, "name": "Derivo Erich", "birth": 1961}