{"sex": "F", "races": {"Pfingstlauf Wohlen AG": {"race": "Pfingstlauf Wohlen AG", "longitude": 8.2768762, "latitude": 47.3493653, "date": {"sam. 26.05.2007": {"weekday": "saturday", "year": 2007, "categories": {"F40": {"pace": 369000000000, "rank": 43, "distance": 8, "time": 3028.2}}, "day": 26, "month": 5, "livingplace": "Brugg"}, "sam. 03.06.2006": {"weekday": "saturday", "year": 2006, "categories": {"F40": {"pace": 350000000000, "rank": 54, "distance": 8, "time": 2876.8}}, "day": 3, "month": 6, "livingplace": "Brugg"}, "sam. 14.05.2005": {"weekday": "saturday", "year": 2005, "categories": {"F40": {"pace": 345000000000, "rank": 41, "distance": 8, "time": 2829.9}}, "day": 14, "month": 5, "livingplace": "Brugg"}, "sam. 10.05.2008": {"weekday": "saturday", "year": 2008, "categories": {"F40": {"pace": 390000000000, "rank": 30, "distance": 8, "time": 3205.6}}, "day": 10, "month": 5, "livingplace": "Brugg"}}, "location": "Wohlen AG"}, "Kerzerslauf": {"race": "Kerzerslauf", "longitude": 7.1954365, "latitude": 46.97488999999999, "date": {"sam. 20.03.2010": {"weekday": "saturday", "year": 2010, "categories": {"15-W15": {"pace": 532000000000, "rank": 240, "distance": 15, "time": 7981.1}}, "day": 20, "month": 3, "livingplace": "Brugg"}}, "location": "Kerzers"}, "Gippinger Stauseelauf": {"race": "Gippinger Stauseelauf", "longitude": 8.2152586, "latitude": 47.5810513, "date": {"dim. 31.12.2006": {"weekday": "sunday", "year": 2006, "categories": {"F40": {"pace": 356000000000, "rank": 89, "distance": 8, "time": 2670.8}}, "day": 31, "month": 12, "livingplace": "Brugg"}}, "location": "Leuggern"}, "ASICS Bremgarter Reusslauf": {"race": "ASICS Bremgarter Reusslauf", "longitude": 8.3397905, "latitude": 47.34917739999999, "date": {"sam. 17.02.2007": {"weekday": "saturday", "year": 2007, "categories": {"F40": {"pace": 357000000000, "rank": 204, "distance": 11, "time": 3754.3}}, "day": 17, "month": 2, "livingplace": "Brugg"}}, "location": "Bremgarten AG"}, "Herbstlauf Muri AG": {"race": "Herbstlauf Muri AG", "date": {"sam. 26.08.2006": {"weekday": "saturday", "year": 2006, "categories": {"F40": {"pace": 362000000000, "rank": 26, "distance": 10, "time": 3625.4}}, "day": 26, "month": 8, "livingplace": "Brugg"}, "sam. 25.08.2007": {"weekday": "saturday", "year": 2007, "categories": {"F40": {"pace": 388000000000, "rank": 32, "distance": 10, "time": 3882.8}}, "day": 25, "month": 8, "livingplace": "Brugg"}}, "location": "Muri AG"}}, "name": "Desteffani Maggie", "birth": 1962}