{"sex": "M", "races": {"Hallwilerseelauf, Beinwil am See": {"race": "Hallwilerseelauf, Beinwil am See", "date": {"sam. 14.10.2006": {"weekday": "saturday", "year": 2006, "categories": {"M50": {"pace": 309000000000, "rank": 213, "distance": 21, "time": 6535.0}}, "day": 14, "month": 10, "livingplace": "Basel"}}, "location": "Beinwil am See"}, "ASICS Bremgarter Reusslauf": {"race": "ASICS Bremgarter Reusslauf", "longitude": 8.3397905, "latitude": 47.34917739999999, "date": {"sam. 17.02.2007": {"weekday": "saturday", "year": 2007, "categories": {"M50": {"pace": 284000000000, "rank": 224, "distance": 11, "time": 2984.5}}, "day": 17, "month": 2, "livingplace": "Basel"}}, "location": "Bremgarten AG"}}, "name": "Fesli Mehmet", "birth": 0}