{"sex": "M", "races": {"Birslauf Basel": {"race": "Birslauf Basel", "longitude": 7.5885761, "latitude": 47.5595986, "date": {"sam. 27.03.2010": {"weekday": "saturday", "year": 2010, "categories": {"M": {"pace": 304000000000, "rank": 332, "distance": 10, "time": 3046.0}}, "day": 27, "month": 3, "livingplace": "Rodersdorf"}}, "location": "Basel"}, "Basel City Marathon": {"race": "Basel City Marathon", "longitude": 7.5885761, "latitude": 47.5595986, "date": {"dim. 03.09.2006": {"weekday": "sunday", "year": 2006, "categories": {"H-M40": {"pace": 295000000000, "rank": 100, "distance": 21, "time": 6237.9}}, "day": 3, "month": 9, "livingplace": "Dornach"}}, "location": "Basel"}, "Muttenzer Herbstlauf": {"race": "Muttenzer Herbstlauf", "longitude": 7.6476369, "latitude": 47.5279292, "date": {"dim. 28.10.2012": {"weekday": "sunday", "year": 2012, "categories": {"5-Mann": {"pace": 330000000000, "rank": 16, "distance": 6, "time": 1848.8}}, "day": 28, "month": 10, "livingplace": "Rodersdorf"}, "dim. 27.10.2013": {"weekday": "sunday", "year": 2013, "categories": {"5-Mann": {"pace": 316000000000, "rank": 18, "distance": 6, "time": 1775.0}}, "day": 27, "month": 10, "livingplace": "Rodersdorf"}}, "location": "Muttenz"}, "Hallwilerseelauf, Beinwil am See": {"race": "Hallwilerseelauf, Beinwil am See", "date": {"sam. 16.10.2010": {"weekday": "saturday", "year": 2010, "categories": {"21-M50": {"pace": 358000000000, "rank": 426, "distance": 21, "time": 7567.5}}, "day": 16, "month": 10, "livingplace": "Rodersdorf"}, "sam. 15.10.2011": {"weekday": "saturday", "year": 2011, "categories": {"21-M50": {"pace": 323000000000, "rank": 369, "distance": 21, "time": 6831.5}}, "day": 15, "month": 10, "livingplace": "Rodersdorf"}, "sam. 10.10.2009": {"weekday": "saturday", "year": 2009, "categories": {"21-M50": {"pace": 331000000000, "rank": 386, "distance": 21, "time": 6988.7}}, "day": 10, "month": 10, "livingplace": "Rodersdorf"}}, "location": "Beinwil am See"}, "ASICS Bremgarter Reusslauf": {"race": "ASICS Bremgarter Reusslauf", "longitude": 8.3397905, "latitude": 47.34917739999999, "date": {"sam. 26.02.2011": {"weekday": "saturday", "year": 2011, "categories": {"M50": {"pace": 305000000000, "rank": 314, "distance": 11, "time": 3359.4}}, "day": 26, "month": 2, "livingplace": "Rodersdorf"}}, "location": "Bremgarten AG"}, "Gempenlauf, Dornach": {"race": "Gempenlauf, Dornach", "longitude": 7.6170412, "latitude": 47.4790491, "date": {"mer. 03.06.2009": {"weekday": "wednesday", "year": 2009, "categories": {"M50": {"pace": 385000000000, "rank": 67, "distance": 8, "time": 3010.2}}, "day": 3, "month": 6, "livingplace": "Rodersdorf"}, "mer. 02.06.2010": {"weekday": "wednesday", "year": 2010, "categories": {"M50": {"pace": 393000000000, "rank": 82, "distance": 8, "time": 3066.0}}, "day": 2, "month": 6, "livingplace": "Rodersdorf"}}, "location": "Dornach"}, "Morat-Fribourg": {"race": "Morat-Fribourg", "longitude": 7.120184, "latitude": 46.92922110000001, "date": {"sam. 01.10.2011": {"weekday": "saturday", "year": 2011, "categories": {"8-JoggM": {"pace": 308000000000, "rank": 73, "distance": 9, "time": 2652.7}}, "day": 1, "month": 10, "livingplace": "Rodersdorf"}}, "location": "Murten"}, "Basler Stadtlauf": {"race": "Basler Stadtlauf", "longitude": 7.5885761, "latitude": 47.5595986, "date": {"sam. 29.11.2008": {"weekday": "saturday", "year": 2008, "categories": {"X": {"pace": 314000000000, "rank": 274, "distance": 6, "time": 1731.2}}, "day": 29, "month": 11, "livingplace": "Rodersdorf"}, "sam. 27.11.2004": {"weekday": "saturday", "year": 2004, "categories": {"U": {"pace": 312000000000, "rank": 330, "distance": 6, "time": 1718.4}}, "day": 27, "month": 11, "livingplace": "Dornach"}, "sam. 29.11.2003": {"weekday": "saturday", "year": 2003, "categories": {"U": {"pace": 324000000000, "rank": 305, "distance": 6, "time": 1784.8}}, "day": 29, "month": 11, "livingplace": "Dornach"}, "sam. 25.11.2006": {"weekday": "saturday", "year": 2006, "categories": {"U": {"pace": 277000000000, "rank": 209, "distance": 6, "time": 1528.0}}, "day": 25, "month": 11, "livingplace": "Dornach"}, "sam. 24.11.2007": {"weekday": "saturday", "year": 2007, "categories": {"U": {"pace": 283000000000, "rank": 262, "distance": 6, "time": 1559.1}}, "day": 24, "month": 11, "livingplace": "Rodersdorf"}, "sam. 26.11.2005": {"weekday": "saturday", "year": 2005, "categories": {"U": {"pace": 282000000000, "rank": 245, "distance": 6, "time": 1552.0}}, "day": 26, "month": 11, "livingplace": "Dornach"}}, "location": "Basel"}, "Derendinger Abendlauf, Derendingen": {"race": "Derendinger Abendlauf, Derendingen", "longitude": 7.585593099999999, "latitude": 47.1952433, "date": {"ven. 27.06.2008": {"weekday": "friday", "year": 2008, "categories": {"M50": {"pace": 305000000000, "rank": 36, "distance": 11, "time": 3264.8}}, "day": 27, "month": 6, "livingplace": "Rodersdorf"}, "ven. 27.06.2014": {"weekday": "friday", "year": 2014, "categories": {"5-VM": {"pace": 332000000000, "rank": 25, "distance": 5, "time": 1793.3}}, "day": 27, "month": 6, "livingplace": "Rodersdorf"}, "ven. 29.06.2007": {"weekday": "friday", "year": 2007, "categories": {"S2": {"pace": 285000000000, "rank": 53, "distance": 11, "time": 3059.8}}, "day": 29, "month": 6, "livingplace": "Dornach"}, "ven. 24.06.2011": {"weekday": "friday", "year": 2011, "categories": {"VLM": {"pace": 299000000000, "rank": 31, "distance": 6, "time": 1707.8}}, "day": 24, "month": 6, "livingplace": "Rodersdorf"}, "ven. 25.06.2010": {"weekday": "friday", "year": 2010, "categories": {"VLM": {"pace": 356000000000, "rank": 29, "distance": 5, "time": 1924.3}}, "day": 25, "month": 6, "livingplace": "Rodersdorf"}, "ven. 26.06.2009": {"weekday": "friday", "year": 2009, "categories": {"M50": {"pace": 298000000000, "rank": 29, "distance": 11, "time": 3195.4}}, "day": 26, "month": 6, "livingplace": "Rodersdorf"}}, "location": "Derendingen"}, "Dreil\u00e4nder-Lauf, Basel": {"race": "Dreil\u00e4nder-Lauf, Basel", "longitude": 7.5885761, "latitude": 47.5595986, "date": {"dim. 17.05.2009": {"weekday": "sunday", "year": 2009, "categories": {"10M50": {"pace": 310000000000, "rank": 9, "distance": 10, "time": 3134.9}}, "day": 17, "month": 5, "livingplace": "Rodersdorf"}}, "location": "Basel"}, "GP Fricktal, Eiken": {"race": "GP Fricktal, Eiken", "date": {"sam. 07.04.2012": {"weekday": "saturday", "year": 2012, "categories": {"Herren3": {"pace": 291000000000, "rank": 22, "distance": 6, "time": 1704.4}}, "day": 7, "month": 4, "livingplace": "Rodersdorf"}}, "location": "Eiken"}, "Kerzerslauf": {"race": "Kerzerslauf", "longitude": 7.1954365, "latitude": 46.97488999999999, "date": {"sam. 20.03.2010": {"weekday": "saturday", "year": 2010, "categories": {"15-M50": {"pace": 325000000000, "rank": 353, "distance": 15, "time": 4879.6}}, "day": 20, "month": 3, "livingplace": "Rodersdorf"}, "sam. 17.03.2012": {"weekday": "saturday", "year": 2012, "categories": {"15-M50": {"pace": 315000000000, "rank": 304, "distance": 15, "time": 4734.2}}, "day": 17, "month": 3, "livingplace": "Rodersdorf"}}, "location": "Kerzers"}}, "name": "Fritz Volkmar", "birth": 1958}