{"sex": "M", "races": {"Frauenfelder": {"race": "Frauenfelder", "date": {"dim. 17.11.2002": {"weekday": "sunday", "year": 2002, "categories": {"M50": {"pace": 468000000000, "rank": 90, "distance": 42, "time": 19765.1}}, "day": 17, "month": 11, "livingplace": "Stein"}, "dim. 16.11.2003": {"weekday": "sunday", "year": 2003, "categories": {"M50": {"pace": 465000000000, "rank": 93, "distance": 42, "time": 19661.2}}, "day": 16, "month": 11, "livingplace": "Stein"}, "dim. 21.11.2004": {"weekday": "sunday", "year": 2004, "categories": {"M50": {"pace": 455000000000, "rank": 85, "distance": 42, "time": 19229.2}}, "day": 21, "month": 11, "livingplace": "Stein"}, "dim. 20.11.2005": {"weekday": "sunday", "year": 2005, "categories": {"M50": {"pace": 472000000000, "rank": 80, "distance": 42, "time": 19931.7}}, "day": 20, "month": 11, "livingplace": "Stein"}, "dim. 18.11.2001": {"weekday": "sunday", "year": 2001, "categories": {"M50": {"pace": 442000000000, "rank": 88, "distance": 42, "time": 18656.4}}, "day": 18, "month": 11, "livingplace": "Stein"}}, "location": "Frauenfeld"}}, "name": "Gfr Oswald Heinz", "birth": 1944}