{"sex": "M", "races": {"Int Greifenseelauf, Uster": {"race": "Int Greifenseelauf, Uster", "longitude": 8.717873899999999, "latitude": 47.3482747, "date": {"sam. 22.09.2007": {"weekday": "saturday", "year": 2007, "categories": {"H/M30": {"pace": 363000000000, "rank": 578, "distance": 21, "time": 7668.6}}, "day": 22, "month": 9, "livingplace": "Wettswil"}}, "location": "Uster"}, "Lucerne Marathon, Luzern": {"race": "Lucerne Marathon, Luzern", "longitude": 8.3093072, "latitude": 47.05016819999999, "date": {"dim. 30.10.2011": {"weekday": "sunday", "year": 2011, "categories": {"H-M30": {"pace": 260000000000, "rank": 166, "distance": 21, "time": 5489.9}}, "day": 30, "month": 10, "livingplace": "Steinhausen"}}, "location": "Luzern"}, "Z\u00fcrcher Silvesterlauf, Z\u00fcrich": {"race": "Z\u00fcrcher Silvesterlauf, Z\u00fcrich", "longitude": 8.541694, "latitude": 47.3768866, "date": {"dim. 16.12.2007": {"weekday": "sunday", "year": 2007, "categories": {"MenAK1-8": {"pace": 348000000000, "rank": 1280, "distance": 9, "time": 2999.3}}, "day": 16, "month": 12, "livingplace": "Wettswil"}}, "location": "Z\u00fcrich"}, "Sempacherseelauf, Sursee": {"race": "Sempacherseelauf, Sursee", "date": {"sam. 08.05.2010": {"weekday": "saturday", "year": 2010, "categories": {"21M30": {"pace": 360000000000, "rank": 185, "distance": 21, "time": 7600.7}}, "day": 8, "month": 5, "livingplace": "Affoltern am Albis"}}, "location": "Sursee"}}, "name": "Gijseman Olaf", "birth": 1976}