{"sex": "M", "races": {"Thuner Langstreckenlauf": {"race": "Thuner Langstreckenlauf", "longitude": 7.6279881, "latitude": 46.7579868, "date": {"sam. 22.05.2004": {"weekday": "saturday", "year": 2004, "categories": {"M30": {"pace": 216000000000, "rank": 8, "distance": 15, "time": 3142.7}}, "day": 22, "month": 5, "livingplace": "Lenk"}}, "location": "Thun"}, "Z\u00fcrich Marathon, Teamrun und Cityrun": {"race": "Z\u00fcrich Marathon, Teamrun und Cityrun", "longitude": 8.541694, "latitude": 47.3768866, "date": {"dim. 09.04.2006": {"weekday": "sunday", "year": 2006, "categories": {"M30": {"pace": 244000000000, "rank": 83, "distance": 42, "time": 10336.1}}, "day": 9, "month": 4, "livingplace": "Lenk im Simmental"}}, "location": "Z\u00fcrich"}, "M\u00e4nnlichen Halbmarathon, Grindelwald": {"race": "M\u00e4nnlichen Halbmarathon, Grindelwald", "longitude": 8.0413962, "latitude": 46.624164, "date": {"dim. 03.06.2012": {"weekday": "sunday", "year": 2012, "categories": {"M30": {"pace": 363000000000, "rank": 3, "distance": 21, "time": 7679.3}}, "day": 3, "month": 6, "livingplace": "Lenk im Simmental"}}, "location": "Grindelwald"}, "Bl\u00fcemlisalp-Lauf, Reichenbach": {"race": "Bl\u00fcemlisalp-Lauf, Reichenbach", "longitude": 7.6940529, "latitude": 46.6254387, "date": {"dim. 30.05.2010": {"weekday": "sunday", "year": 2010, "categories": {"M30": {"pace": 290000000000, "rank": 7, "distance": 16, "time": 4667.5}}, "day": 30, "month": 5, "livingplace": "Lenk im Simmental"}}, "location": "Reichenbach im Kandertal"}, "Basel City Marathon": {"race": "Basel City Marathon", "longitude": 7.5885761, "latitude": 47.5595986, "date": {"dim. 03.09.2006": {"weekday": "sunday", "year": 2006, "categories": {"H-M30": {"pace": 225000000000, "rank": 4, "distance": 21, "time": 4753.4}}, "day": 3, "month": 9, "livingplace": "Lenk im Simmental"}}, "location": "Basel"}, "Hallwilerseelauf, Beinwil am See": {"race": "Hallwilerseelauf, Beinwil am See", "date": {"sam. 10.10.2009": {"weekday": "saturday", "year": 2009, "categories": {"21-M30": {"pace": 243000000000, "rank": 50, "distance": 21, "time": 5140.6}}, "day": 10, "month": 10, "livingplace": "Lenk im Simmental"}}, "location": "Beinwil am See"}, "Kerzerslauf": {"race": "Kerzerslauf", "longitude": 7.1954365, "latitude": 46.97488999999999, "date": {"sam. 18.03.2006": {"weekday": "saturday", "year": 2006, "categories": {"M20": {"pace": 225000000000, "rank": 63, "distance": 15, "time": 3386.1}}, "day": 18, "month": 3, "livingplace": "Lenk im Simmental"}}, "location": "Kerzers"}, "Morat-Fribourg": {"race": "Morat-Fribourg", "longitude": 7.120184, "latitude": 46.92922110000001, "date": {"sam. 06.10.2007": {"weekday": "saturday", "year": 2007, "categories": {"C/M20": {"pace": 228000000000, "rank": 30, "distance": 17, "time": 3920.3}}, "day": 6, "month": 10, "livingplace": "Lenk im Simmental"}}, "location": "Murten"}, "10km de Payerne": {"race": "10km de Payerne", "longitude": 6.9405663, "latitude": 46.8220266, "date": {"sam. 27.03.2010": {"weekday": "saturday", "year": 2010, "categories": {"M35": {"pace": 217000000000, "rank": 15, "distance": 10, "time": 2175.0}}, "day": 27, "month": 3, "livingplace": "Lenk im Simmental"}}, "location": "Payerne"}, "Glacier 3000 Run, Gstaad": {"race": "Glacier 3000 Run, Gstaad", "longitude": 7.2865728, "latitude": 46.4717588, "date": {"sam. 04.08.2012": {"weekday": "saturday", "year": 2012, "categories": {"M30": {"pace": 390000000000, "rank": 7, "distance": 26, "time": 10154.0}}, "day": 4, "month": 8, "livingplace": "Lenk im Simmental"}}, "location": "Gstaad"}, "Steinh\u00f6lzlilauf, Liebefeld": {"race": "Steinh\u00f6lzlilauf, Liebefeld", "longitude": 7.416668, "latitude": 46.933331, "date": {"dim. 05.12.2010": {"weekday": "sunday", "year": 2010, "categories": {"L_S1M": {"pace": 248000000000, "rank": 4, "distance": 11, "time": 2607.1}}, "day": 5, "month": 12, "livingplace": "Lenk im Simmental"}}, "location": "Liebefeld"}, "Burgdorfer Stadtlauf, Burgdorf": {"race": "Burgdorfer Stadtlauf, Burgdorf", "longitude": -115.9129022, "latitude": 45.277123, "date": {"sam. 15.09.2007": {"weekday": "saturday", "year": 2007, "categories": {"MHE1": {"pace": 226000000000, "rank": 2, "distance": 8, "time": 1808.7}}, "day": 15, "month": 9, "livingplace": "Lenk im Simmental"}}, "location": "Burgdorf"}, "Internationaler Matterhornlauf, Zermatt": {"race": "Internationaler Matterhornlauf, Zermatt", "date": {"dim. 21.08.2005": {"weekday": "sunday", "year": 2005, "categories": {"MHL/M30": {"pace": 346000000000, "rank": 13, "distance": 14, "time": 4974.4}}, "day": 21, "month": 8, "livingplace": "Lenk im Simmental"}}, "location": "Zermatt"}, "Jungfrau-Marathon, Interlaken": {"race": "Jungfrau-Marathon, Interlaken", "date": {"sam. 08.09.2012": {"weekday": "saturday", "year": 2012, "categories": {"SO-M20": {"pace": 323000000000, "rank": 72, "distance": 42, "time": 13658.0}}, "day": 8, "month": 9, "livingplace": "Lenk im Simmental"}}, "location": "Interlaken"}, "Aletsch-Halbmarathon, Bettmeralp": {"race": "Aletsch-Halbmarathon, Bettmeralp", "date": {"dim. 24.06.2012": {"weekday": "sunday", "year": 2012, "categories": {"M30": {"pace": 322000000000, "rank": 16, "distance": 21, "time": 6844.7}}, "day": 24, "month": 6, "livingplace": "Lenk im Simmental"}}, "location": "Bettmeralp"}}, "name": "Gobeli Kurt", "birth": 1973}