{"sex": "M", "races": {"Hallwilerseelauf, Beinwil am See": {"race": "Hallwilerseelauf, Beinwil am See", "date": {"sam. 10.10.2015": {"weekday": "saturday", "year": 2015, "categories": {"10-Mjun": {"pace": 267000000000, "rank": 16, "distance": 10, "time": 2679.1}}, "day": 10, "month": 10, "livingplace": "Lenzburg"}}, "location": "Beinwil am See"}, "Lenzburger Lauf": {"race": "Lenzburger Lauf", "longitude": 8.172154500000001, "latitude": 47.3904443, "date": {"sam. 30.05.2015": {"weekday": "saturday", "year": 2015, "categories": {"Jun-M": {"pace": 271000000000, "rank": 2, "distance": 5, "time": 1437.2}}, "day": 30, "month": 5, "livingplace": "FC Lenzburg"}, "sam. 29.05.2010": {"weekday": "saturday", "year": 2010, "categories": {"Ober1M": {"pace": 287000000000, "rank": 10, "distance": 3, "time": 747.0}}, "day": 29, "month": 5, "livingplace": "R1A"}, "sam. 24.05.2008": {"weekday": "saturday", "year": 2008, "categories": {"SBM": {"pace": 199000000000, "rank": 6, "distance": 3, "time": 537.3}}, "day": 24, "month": 5, "livingplace": "Lenzburg"}, "sam. 25.05.2013": {"weekday": "saturday", "year": 2013, "categories": {"JunA-M": {"pace": 280000000000, "rank": 3, "distance": 5, "time": 1484.0}}, "day": 25, "month": 5, "livingplace": "Suhr"}, "sam. 28.05.2011": {"weekday": "saturday", "year": 2011, "categories": {"Ober1M": {"pace": 255000000000, "rank": 18, "distance": 2, "time": 511.4}}, "day": 28, "month": 5, "livingplace": "S2A"}}, "location": "Lenzburg"}}, "name": "H\u00e4fliger Roger", "birth": 1997}