{"sex": "M", "races": {"Lucerne Marathon, Luzern": {"race": "Lucerne Marathon, Luzern", "longitude": 8.3093072, "latitude": 47.05016819999999, "date": {"dim. 25.10.2009": {"weekday": "sunday", "year": 2009, "categories": {"H-M40": {"pace": 289000000000, "rank": 401, "distance": 21, "time": 6103.2}}, "day": 25, "month": 10, "livingplace": "Arth"}, "dim. 31.10.2010": {"weekday": "sunday", "year": 2010, "categories": {"H-M40": {"pace": 294000000000, "rank": 470, "distance": 21, "time": 6205.6}}, "day": 31, "month": 10, "livingplace": "Arth"}}, "location": "Luzern"}, "Rotseelauf, Ebikon": {"race": "Rotseelauf, Ebikon", "date": {"sam. 04.04.2009": {"weekday": "saturday", "year": 2009, "categories": {"M40": {"pace": 305000000000, "rank": 156, "distance": 10, "time": 3053.7}}, "day": 4, "month": 4, "livingplace": "Arth"}, "sam. 21.04.2007": {"weekday": "saturday", "year": 2007, "categories": {"M40": {"pace": 293000000000, "rank": 109, "distance": 10, "time": 2936.6}}, "day": 21, "month": 4, "livingplace": "Arth"}, "sam. 01.04.2006": {"weekday": "saturday", "year": 2006, "categories": {"M40": {"pace": 276000000000, "rank": 79, "distance": 10, "time": 2769.7}}, "day": 1, "month": 4, "livingplace": "Arth"}}, "location": "Ebikon"}}, "name": "Heimoz Martin", "birth": 1965}