{"sex": "M", "races": {"Z\u00fcrich Marathon, Teamrun und Cityrun": {"race": "Z\u00fcrich Marathon, Teamrun und Cityrun", "longitude": 8.541694, "latitude": 47.3768866, "date": {"dim. 07.04.2013": {"weekday": "sunday", "year": 2013, "categories": {"10-M30": {"pace": 306000000000, "rank": 188, "distance": 10, "time": 3066.6}}, "day": 7, "month": 4, "livingplace": "Montlingen"}}, "location": "Z\u00fcrich"}, "Frauenfelder": {"race": "Frauenfelder", "date": {"dim. 17.11.2013": {"weekday": "sunday", "year": 2013, "categories": {"HM-M30": {"pace": 296000000000, "rank": 151, "distance": 21, "time": 6256.4}}, "day": 17, "month": 11, "livingplace": "Montlingen"}}, "location": "Frauenfeld"}, "Winterthur Marathon": {"race": "Winterthur Marathon", "longitude": -75.6037351, "latitude": 39.8088766, "date": {"dim. 26.05.2013": {"weekday": "sunday", "year": 2013, "categories": {"10-M30": {"pace": 314000000000, "rank": 43, "distance": 10, "time": 3145.8}}, "day": 26, "month": 5, "livingplace": "Montlingen"}}, "location": "Winterthur"}}, "name": "Huber Beat", "birth": 1976}