{"sex": "M", "races": {"Int Greifenseelauf, Uster": {"race": "Int Greifenseelauf, Uster", "longitude": 8.717873899999999, "latitude": 47.3482747, "date": {"sam. 20.09.2003": {"weekday": "saturday", "year": 2003, "categories": {"H/M60": {"pace": 383000000000, "rank": 84, "distance": 21, "time": 8085.1}}, "day": 20, "month": 9, "livingplace": "Zurich"}, "sam. 22.09.2007": {"weekday": "saturday", "year": 2007, "categories": {"H/M65": {"pace": 405000000000, "rank": 62, "distance": 21, "time": 8553.0}}, "day": 22, "month": 9, "livingplace": "Zurich"}, "sam. 16.09.2006": {"weekday": "saturday", "year": 2006, "categories": {"H/M60": {"pace": 430000000000, "rank": 159, "distance": 21, "time": 9084.0}}, "day": 16, "month": 9, "livingplace": "Zurich"}}, "location": "Uster"}, "Z\u00fcrcher Silvesterlauf, Z\u00fcrich": {"race": "Z\u00fcrcher Silvesterlauf, Z\u00fcrich", "longitude": 8.541694, "latitude": 47.3768866, "date": {"dim. 14.12.2008": {"weekday": "sunday", "year": 2008, "categories": {"MenAK4-8": {"pace": 377000000000, "rank": 177, "distance": 9, "time": 3242.4}}, "day": 14, "month": 12, "livingplace": "Zurich"}, "dim. 10.12.2006": {"weekday": "sunday", "year": 2006, "categories": {"MenAK4-8": {"pace": 338000000000, "rank": 142, "distance": 9, "time": 2914.8}}, "day": 10, "month": 12, "livingplace": "Zurich"}, "dim. 13.12.2009": {"weekday": "sunday", "year": 2009, "categories": {"8-MenAK4": {"pace": 390000000000, "rank": 192, "distance": 9, "time": 3360.8}}, "day": 13, "month": 12, "livingplace": "Zurich"}}, "location": "Z\u00fcrich"}, "Basler Marathon-Tage": {"race": "Basler Marathon-Tage", "longitude": 7.5885761, "latitude": 47.5595986, "date": {"sam. 27.10.2007": {"weekday": "saturday", "year": 2007, "categories": {"HM/M60": {"pace": 394000000000, "rank": 21, "distance": 21, "time": 8326.6}}, "day": 27, "month": 10, "livingplace": "Zurich"}}, "location": "Basel"}, "Basler Stadtlauf": {"race": "Basler Stadtlauf", "longitude": 7.5885761, "latitude": 47.5595986, "date": {"sam. 24.11.2007": {"weekday": "saturday", "year": 2007, "categories": {"X": {"pace": 333000000000, "rank": 130, "distance": 6, "time": 1832.8}}, "day": 24, "month": 11, "livingplace": "Zurich"}, "sam. 25.11.2006": {"weekday": "saturday", "year": 2006, "categories": {"X": {"pace": 325000000000, "rank": 93, "distance": 6, "time": 1791.2}}, "day": 25, "month": 11, "livingplace": "Zurich"}, "sam. 24.11.2012": {"weekday": "saturday", "year": 2012, "categories": {"M70": {"pace": 395000000000, "rank": 30, "distance": 6, "time": 2174.6}}, "day": 24, "month": 11, "livingplace": "Zurich"}}, "location": "Basel"}, "Walliseller Lauf, Wallisellen": {"race": "Walliseller Lauf, Wallisellen", "date": {"dim. 05.11.2006": {"weekday": "sunday", "year": 2006, "categories": {"M5": {"pace": 358000000000, "rank": 27, "distance": 10, "time": 3407.3}}, "day": 5, "month": 11, "livingplace": "Zurich"}}, "location": "Wallisellen"}}, "name": "Kaiser Christian", "birth": 1942}