{"sex": "M", "races": {"Int Greifenseelauf, Uster": {"race": "Int Greifenseelauf, Uster", "longitude": 8.717873899999999, "latitude": 47.3482747, "date": {"sam. 22.09.2007": {"weekday": "saturday", "year": 2007, "categories": {"H/M40": {"pace": 214000000000, "rank": 2, "distance": 21, "time": 4523.8}}, "day": 22, "month": 9, "livingplace": "Freiburg"}, "sam. 16.09.2006": {"weekday": "saturday", "year": 2006, "categories": {"H/M40": {"pace": 209000000000, "rank": 2, "distance": 21, "time": 4410.3}}, "day": 16, "month": 9, "livingplace": "D"}}, "location": "Uster"}, "Jungfrau-Marathon, Interlaken": {"race": "Jungfrau-Marathon, Interlaken", "date": {"sam. 05.09.2009": {"weekday": "saturday", "year": 2009, "categories": {"M45": {"pace": 341000000000, "rank": 29, "distance": 42, "time": 14426.6}}, "day": 5, "month": 9, "livingplace": "Ehrenkirchen"}, "sam. 06.09.2008": {"weekday": "saturday", "year": 2008, "categories": {"M40": {"pace": 305000000000, "rank": 4, "distance": 42, "time": 12895.8}}, "day": 6, "month": 9, "livingplace": "Ehrenkirchen"}}, "location": "Interlaken"}, "Basler Stadtlauf": {"race": "Basler Stadtlauf", "longitude": 7.5885761, "latitude": 47.5595986, "date": {"sam. 24.11.2001": {"weekday": "saturday", "year": 2001, "categories": {"Y": {"pace": 194000000000, "rank": 36, "distance": 10, "time": 1941.4}}, "day": 24, "month": 11, "livingplace": "Freiburg"}}, "location": "Basel"}}, "name": "Kelter Gerhard", "birth": 1964}