{"sex": "F", "races": {"Hellebardenlauf Sempach": {"race": "Hellebardenlauf Sempach", "date": {"sam. 14.06.2014": {"weekday": "saturday", "year": 2014, "categories": {"U8-W": {"pace": 331000000000, "rank": 46, "distance": 1, "time": 198.9}}, "day": 14, "month": 6, "livingplace": "Reitnau"}}, "location": "Sempach Stadt"}, "Lenzburger Lauf": {"race": "Lenzburger Lauf", "longitude": 8.172154500000001, "latitude": 47.3904443, "date": {"sam. 30.05.2015": {"weekday": "saturday", "year": 2015, "categories": {"Piccola": {"pace": 285000000000, "rank": 9, "distance": 1, "time": 228.0}}, "day": 30, "month": 5, "livingplace": "Reitnau"}}, "location": "Lenzburg"}}, "name": "Lehmann Lea", "birth": 2008}