{"sex": "M", "races": {"Course de l'Escalade, Gen\u00e8ve": {"race": "Course de l'Escalade, Gen\u00e8ve", "longitude": 6.1431577, "latitude": 46.2043907, "date": {"sam. 03.12.2011": {"weekday": "saturday", "year": 2011, "categories": {"H-H4": {"pace": 268000000000, "rank": 157, "distance": 7, "time": 1948.2}}, "day": 3, "month": 12, "livingplace": "Vesenaz"}, "sam. 01.12.2012": {"weekday": "saturday", "year": 2012, "categories": {"Duc-Hom4": {"pace": 291000000000, "rank": 99, "distance": 18, "time": 5099.2}}, "day": 1, "month": 12, "livingplace": "Vesenaz"}, "sam. 04.12.2010": {"weekday": "saturday", "year": 2010, "categories": {"H-H3": {"pace": 256000000000, "rank": 450, "distance": 7, "time": 1858.5}}, "day": 4, "month": 12, "livingplace": "Vesenaz"}, "sam. 06.12.2014": {"weekday": "saturday", "year": 2014, "categories": {"Esc-Hom4": {"pace": 293000000000, "rank": 368, "distance": 7, "time": 2146.5}}, "day": 6, "month": 12, "livingplace": "Geneve"}, "sam. 05.12.2015": {"weekday": "saturday", "year": 2015, "categories": {"Esc-Hom4": {"pace": 291000000000, "rank": 412, "distance": 7, "time": 2135.6}}, "day": 5, "month": 12, "livingplace": "Geneve"}, "sam. 07.12.2013": {"weekday": "saturday", "year": 2013, "categories": {"Esc-Hom4": {"pace": 274000000000, "rank": 179, "distance": 7, "time": 1988.2}}, "day": 7, "month": 12, "livingplace": "Vesenaz"}}, "location": "Gen\u00e8ve"}, "Morat-Fribourg": {"race": "Morat-Fribourg", "longitude": 7.120184, "latitude": 46.92922110000001, "date": {"sam. 03.10.2009": {"weekday": "saturday", "year": 2009, "categories": {"C-M45": {"pace": 322000000000, "rank": 417, "distance": 17, "time": 5530.0}}, "day": 3, "month": 10, "livingplace": "Vesenaz"}, "sam. 01.10.2011": {"weekday": "saturday", "year": 2011, "categories": {"17-M50": {"pace": 310000000000, "rank": 223, "distance": 17, "time": 5332.9}}, "day": 1, "month": 10, "livingplace": "Vesenaz"}, "sam. 02.10.2010": {"weekday": "saturday", "year": 2010, "categories": {"17-M45": {"pace": 324000000000, "rank": 393, "distance": 17, "time": 5566.2}}, "day": 2, "month": 10, "livingplace": "Vesenaz"}, "sam. 04.10.2008": {"weekday": "saturday", "year": 2008, "categories": {"C-M45": {"pace": 322000000000, "rank": 471, "distance": 17, "time": 5531.6}}, "day": 4, "month": 10, "livingplace": "Vesenaz"}, "sam. 06.10.2012": {"weekday": "saturday", "year": 2012, "categories": {"17-M50": {"pace": 304000000000, "rank": 199, "distance": 17, "time": 5311.5}}, "day": 6, "month": 10, "livingplace": "Vesenaz"}}, "location": "Murten"}, "Jungfrau-Marathon, Interlaken": {"race": "Jungfrau-Marathon, Interlaken", "date": {"sam. 05.09.2009": {"weekday": "saturday", "year": 2009, "categories": {"M45": {"pace": 464000000000, "rank": 427, "distance": 42, "time": 19602.9}}, "day": 5, "month": 9, "livingplace": "Vesenaz"}}, "location": "Interlaken"}, "SwissCityMarathon - Lucerne, Luzern": {"race": "SwissCityMarathon - Lucerne, Luzern", "longitude": 8.3093072, "latitude": 47.05016819999999, "date": {"dim. 25.10.2015": {"weekday": "sunday", "year": 2015, "categories": {"M-M50": {"pace": 369000000000, "rank": 116, "distance": 42, "time": 15599.7}}, "day": 25, "month": 10, "livingplace": "Geneve"}}, "location": "Luzern"}}, "name": "Mach Fran\u00e7ois", "birth": 1961}