{"sex": "F", "races": {"Engadiner Sommerlauf, Samedan": {"race": "Engadiner Sommerlauf, Samedan", "date": {"dim. 22.08.2010": {"weekday": "sunday", "year": 2010, "categories": {"S-D2": {"pace": 383000000000, "rank": 49, "distance": 27, "time": 10353.7}}, "day": 22, "month": 8, "livingplace": "Therwil"}}, "location": "Bever"}, "Basel City Marathon": {"race": "Basel City Marathon", "longitude": 7.5885761, "latitude": 47.5595986, "date": {"dim. 03.09.2006": {"weekday": "sunday", "year": 2006, "categories": {"M-F30": {"pace": 426000000000, "rank": 55, "distance": 42, "time": 18002.5}}, "day": 3, "month": 9, "livingplace": "Therwil"}}, "location": "Basel"}, "Gempenlauf, Dornach": {"race": "Gempenlauf, Dornach", "longitude": 7.6170412, "latitude": 47.4790491, "date": {"mer. 02.06.2010": {"weekday": "wednesday", "year": 2010, "categories": {"F40": {"pace": 422000000000, "rank": 25, "distance": 8, "time": 3298.7}}, "day": 2, "month": 6, "livingplace": "Therwil"}}, "location": "Dornach"}, "Winterthur Marathon": {"race": "Winterthur Marathon", "longitude": -75.6037351, "latitude": 39.8088766, "date": {"dim. 31.05.2015": {"weekday": "sunday", "year": 2015, "categories": {"HM-F40": {"pace": 375000000000, "rank": 104, "distance": 21, "time": 7885.4}}, "day": 31, "month": 5, "livingplace": "Winterthur"}, "dim. 29.05.2011": {"weekday": "sunday", "year": 2011, "categories": {"H-F40": {"pace": 345000000000, "rank": 68, "distance": 21, "time": 7261.7}}, "day": 29, "month": 5, "livingplace": "Winterthur"}}, "location": "Winterthur"}, "Aletsch-Halbmarathon, Bettmeralp": {"race": "Aletsch-Halbmarathon, Bettmeralp", "date": {"dim. 27.06.2010": {"weekday": "sunday", "year": 2010, "categories": {"F40": {"pace": 546000000000, "rank": 90, "distance": 21, "time": 11477.4}}, "day": 27, "month": 6, "livingplace": "Therwil"}, "dim. 24.06.2012": {"weekday": "sunday", "year": 2012, "categories": {"F45": {"pace": 552000000000, "rank": 104, "distance": 21, "time": 11710.5}}, "day": 24, "month": 6, "livingplace": "Therwil"}}, "location": "Bettmeralp"}, "Int Greifenseelauf, Uster": {"race": "Int Greifenseelauf, Uster", "longitude": 8.717873899999999, "latitude": 47.3482747, "date": {"sam. 19.09.2009": {"weekday": "saturday", "year": 2009, "categories": {"H-W40": {"pace": 356000000000, "rank": 289, "distance": 21, "time": 7517.1}}, "day": 19, "month": 9, "livingplace": "Winterthur"}, "sam. 20.09.2008": {"weekday": "saturday", "year": 2008, "categories": {"H-W40": {"pace": 365000000000, "rank": 340, "distance": 21, "time": 7720.7}}, "day": 20, "month": 9, "livingplace": "Therwil"}}, "location": "Uster"}}, "name": "Meier Sonja", "birth": 1967}