{"sex": "M", "races": {"Zermatt Marathon, Zermatt": {"race": "Zermatt Marathon, Zermatt", "date": {"sam. 06.07.2013": {"weekday": "saturday", "year": 2013, "categories": {"M-STMM\u00e4": {"pace": 391000000000, "rank": 11, "distance": 42, "time": 16510.0}}, "day": 6, "month": 7, "livingplace": "Ehrendingen"}}, "location": "Zermatt"}, "Aletsch-Halbmarathon, Bettmeralp": {"race": "Aletsch-Halbmarathon, Bettmeralp", "date": {"dim. 29.06.2014": {"weekday": "sunday", "year": 2014, "categories": {"M55": {"pace": 392000000000, "rank": 32, "distance": 13, "time": 5222.7}}, "day": 29, "month": 6, "livingplace": "Ehrendingen"}}, "location": "Bettmeralp"}}, "name": "Rother Bharu", "birth": 1959}