{"sex": "M", "races": {"Basler Stadtlauf": {"race": "Basler Stadtlauf", "longitude": 7.5885761, "latitude": 47.5595986, "date": {"sam. 29.11.2008": {"weekday": "saturday", "year": 2008, "categories": {"M": {"pace": 255000000000, "rank": 169, "distance": 6, "time": 1407.0}}, "day": 29, "month": 11, "livingplace": "Daniken"}, "sam. 26.11.2011": {"weekday": "saturday", "year": 2011, "categories": {"M": {"pace": 279000000000, "rank": 319, "distance": 6, "time": 1536.5}}, "day": 26, "month": 11, "livingplace": "Chur"}}, "location": "Basel"}, "Zumiker-Lauf": {"race": "Zumiker-Lauf", "date": {"sam. 05.06.2010": {"weekday": "saturday", "year": 2010, "categories": {"A": {"pace": 283000000000, "rank": 21, "distance": 11, "time": 3179.0}}, "day": 5, "month": 6, "livingplace": "Chur"}}, "location": "Zumikon"}}, "name": "Soltermann Lucas", "birth": 1982}